rootfinding.py
numericalmethodsJB-0.0.1.dist-info/LICENSE.txt
numericalmethodsJB-0.0.1.dist-info/METADATA
numericalmethodsJB-0.0.1.dist-info/WHEEL
numericalmethodsJB-0.0.1.dist-info/top_level.txt
numericalmethodsJB-0.0.1.dist-info/RECORD
